script/__init__.py
script/enigma.py
node_enigma-0.1.0.dist-info/LICENSE
node_enigma-0.1.0.dist-info/METADATA
node_enigma-0.1.0.dist-info/WHEEL
node_enigma-0.1.0.dist-info/entry_points.txt
node_enigma-0.1.0.dist-info/top_level.txt
node_enigma-0.1.0.dist-info/RECORD
