Metadata-Version: 2.1
Name: node-enigma
Version: 0.1.0
Summary: Python Command Line to encrypt and decrypt messages
Home-page: https://github.com/dyeboah/enigma.py
Author: David Yeboah
Author-email: dyeboah@oswego.edu
License: ['MIT']
Platform: UNKNOWN
Requires-Dist: Argparse
Requires-Dist: Requests
